diaper.py
diaper-1.3.dist-info/DESCRIPTION.rst
diaper-1.3.dist-info/WHEEL
diaper-1.3.dist-info/METADATA
diaper-1.3.dist-info/RECORD
diaper-1.3.dist-info/top_level.txt
diaper-1.3.dist-info/metadata.json
